LICENSE
README.rst
enos/__init__.py
enos/ansible/enos.yml
enos/ansible/group_vars/all.yml
enos/ansible/init_os.yml
enos/ansible/plugins/callback/influxdb_events.py
enos/ansible/roles/cadvisor/defaults/main.yml
enos/ansible/roles/cadvisor/tasks/backup.yml
enos/ansible/roles/cadvisor/tasks/bench.yml
enos/ansible/roles/cadvisor/tasks/deploy.yml
enos/ansible/roles/cadvisor/tasks/destroy.yml
enos/ansible/roles/cadvisor/tasks/main.yml
enos/ansible/roles/cadvisor/tasks/pull.yml
enos/ansible/roles/collectd/defaults/main.yml
enos/ansible/roles/collectd/files/collectd.conf
enos/ansible/roles/collectd/files/contextswitch.conf
enos/ansible/roles/collectd/files/haproxy.conf
enos/ansible/roles/collectd/files/haproxy.py
enos/ansible/roles/collectd/files/protocols.conf
enos/ansible/roles/collectd/files/tcpconns-compute.conf
enos/ansible/roles/collectd/files/tcpconns-haproxy.conf
enos/ansible/roles/collectd/files/tcpconns-keystone.conf
enos/ansible/roles/collectd/files/tcpconns-mariadb.conf
enos/ansible/roles/collectd/files/tcpconns-memcached.conf
enos/ansible/roles/collectd/files/tcpconns-network.conf
enos/ansible/roles/collectd/files/tcpconns-nova.conf
enos/ansible/roles/collectd/files/tcpconns-rabbitmq.conf
enos/ansible/roles/collectd/tasks/backup.yml
enos/ansible/roles/collectd/tasks/bench.yml
enos/ansible/roles/collectd/tasks/deploy.yml
enos/ansible/roles/collectd/tasks/destroy.yml
enos/ansible/roles/collectd/tasks/main.yml
enos/ansible/roles/collectd/tasks/pull.yml
enos/ansible/roles/collectd/templates/influx.conf.j2
enos/ansible/roles/collectd/templates/memcached.conf.j2
enos/ansible/roles/collectd/templates/mysql.conf.j2
enos/ansible/roles/collectd/templates/rabbitmq.conf.j2
enos/ansible/roles/grafana/defaults/main.yml
enos/ansible/roles/grafana/tasks/backup.yml
enos/ansible/roles/grafana/tasks/bench.yml
enos/ansible/roles/grafana/tasks/deploy.yml
enos/ansible/roles/grafana/tasks/destroy.yml
enos/ansible/roles/grafana/tasks/main.yml
enos/ansible/roles/grafana/tasks/pull.yml
enos-8.0.0.dist-info/LICENSE
enos-8.0.0.dist-info/METADATA
enos-8.0.0.dist-info/WHEEL
enos-8.0.0.dist-info/entry_points.txt
enos-8.0.0.dist-info/RECORD
