Metadata-Version: 2.1
Name: enos
Version: 8.0.0
Summary: Experimental eNvironment for OpenStack
Home-page: https://github.com/BeyondTheClouds/enos
License: GPL-3.0-or-later
Keywords: OpenStack,Evaluation,Grid'5000,Chameleon,Vagrant
Author: Didier Iscovery
Author-email: discovery-dev@inria.fr
Requires-Python: >=3.8,<4.0
Classifier: Development Status :: 4 - Beta
Classifier: Intended Audience :: Science/Research
Classifier: Intended Audience :: System Administrators
Classifier: License :: OSI Approved :: GNU General Public License v3 or later (GPLv3+)
Classifier: Operating System :: POSIX :: Linux
Classifier: Programming Language :: Python :: 3
Classifier: Programming Language :: Python :: 3.8
Classifier: Programming Language :: Python :: 3.9
Classifier: Programming Language :: Python :: 3.10
Classifier: Programming Language :: Python :: 3.11
Classifier: Programming Language :: Python :: 3.12
Provides-Extra: annotations
Requires-Dist: ansible (>=2.9,<2.10)
Requires-Dist: docopt (>=0.6.2,<0.7.0)
Requires-Dist: enoslib[chameleon] (>=8.4.0,<9.0.0)
Requires-Dist: influxdb (==4.0.0) ; extra == "annotations"
Requires-Dist: python-heatclient (>=2.5.0,<3.0.0)
Requires-Dist: python-openstackclient (>=5.5,<7)
Requires-Dist: virtualenv (>=20.4.3,<21.0.0)
Project-URL: Documentation, https://beyondtheclouds.github.io/enos/
